{"classname":"GameObject","name":null,"canedit":true,"objecttag":-1,"rotation":0,"scalex":1,"scaley":1,"visible":1,"x":0,"y":0,"zorder":-1000000,"gameobjects":[{"__type":"ComGameObjectSurrogate:#EditorCommon.JsonModel","classname":"GameObject","name":"GameObject","canedit":true,"objecttag":-1,"rotation":0,"scalex":1,"scaley":1,"visible":1,"x":283.5,"y":215,"zorder":1,"gameobjects":[],"components":[{"__type":"ComSpriteSurrogate:#EditorCommon.JsonModel.Component","classname":"Sprite","name":null,"file":"","action":0,"enableselfcollider":0,"enabletouch":0,"filetype":-1,"isbigimage":0,"rect":{"classname":null,"name":null,"h":0,"w":0,"x":0,"y":0},"spritedatascale":0,"usebatchnode":0,"userect":0}]},{"__type":"ComGameObjectSurrogate:#EditorCommon.JsonModel","classname":"GameObject","name":null,"canedit":true,"objecttag":-1,"rotation":0,"scalex":1,"scaley":1,"visible":1,"x":179.5,"y":203,"zorder":1,"gameobjects":[],"components":[{"__type":"ComParticleSystemSurrogate:#EditorCommon.JsonModel.Component","classname":"ParticleSystem","name":null,"file":"","autodel":0}]}],"CanvasSize":{"_height":320,"_width":480},"components":[{"__type":"ComSceneSurrogate:#EditorCommon.JsonModel.Component","classname":"Scene","name":"Scene","scenename":"NewProject2"},{"__type":"ComAccelerometerSurrogate:#EditorCommon.JsonModel.Component","classname":"Accelerometer","name":"Accelerometer","enableaccelerometer":0},{"__type":"ComGyroscopeSurrogate:#EditorCommon.JsonModel.Component","classname":"Gyroscope","name":"Gyroscope","enablegyroscope":0},{"__type":"ComPhotoGraphSurrogate:#EditorCommon.JsonModel.Component","classname":"PhotoGraph","name":"PhotoGraph"},{"__type":"ComInputSurrogate:#EditorCommon.JsonModel.Component","classname":"Input","name":"Input","multi":0},{"__type":"ComSimpleAudioSurrogate:#EditorCommon.JsonModel.Component","classname":"SimpleAudioComponent","name":"SimpleAudioComponent","file":null,"loop":0,"pre":0,"volume":50}]}